{
	"type": "regenerative_block",
	"id": "dense_mars_be_ostrum_ore",
	"modsRequired": [
		"minecraft",
		"beyond_earth"
	],
	"toolLevel": 2,
	"hardness": 3.0,
	"luminance": 2,
	"standardTexture": false,
	"infinite": false,
	"silkable": true,
	"replace": true,
	"onlyValidTools": false,
	"englishName": "Dense Mars Ostrum Ore",
	"damageFunction": "default",
	"textureClone": "beyond_earth:block/mars_ostrum_ore",
	"denseOreGenTarget": "beyond_earth:mars_ostrum_ore",
	"denseOreGenReplaceState": false,
	"replaceBlockId": "beyond_earth:mars_stone",
	"lootConfig": {
		"type": "regenerative_ore_loot",
		"silkable": true,
		"ore_set": [
			"beyond_earth:mars_ostrum_ore"
		]
	}
}